pywf/__init__.py
pywf/cpp_pyworkflow.cpython-37m-x86_64-linux-gnu.so
pywf/mysql_iterator.py
pywf-0.0.10.dist-info/LICENSE
pywf-0.0.10.dist-info/METADATA
pywf-0.0.10.dist-info/WHEEL
pywf-0.0.10.dist-info/top_level.txt
pywf-0.0.10.dist-info/RECORD
pywf.libs/libssl-45ea509f.so.1.0.2k
pywf.libs/libz-352360f2.so.1.2.7
pywf.libs/libpcre-6ed78012.so.1.2.0
pywf.libs/libk5crypto-b1f99d5c.so.3.1
pywf.libs/libkrb5support-05003b99.so.0.1
pywf.libs/libcrypto-ca1dbc5f.so.1.0.2k
pywf.libs/libgssapi_krb5-497db0c6.so.2.2
pywf.libs/libkeyutils-dfe70bd6.so.1.5
pywf.libs/libcom_err-8978d250.so.2.1
pywf.libs/libkrb5-fc820a1d.so.3.3
pywf.libs/libselinux-f8b6b948.so.1
